dagster_pandera/__init__.py
dagster_pandera/py.typed
dagster_pandera/version.py
dagster_pandera-1.0.5.dist-info/LICENSE
dagster_pandera-1.0.5.dist-info/METADATA
dagster_pandera-1.0.5.dist-info/WHEEL
dagster_pandera-1.0.5.dist-info/top_level.txt
dagster_pandera-1.0.5.dist-info/RECORD
