Metadata-Version: 2.1
Name: dagster-pandera
Version: 1.0.5
Summary: Integration layer for dagster and pandera.
Home-page: https://github.com/dagster-io/dagster
Author: Elementl
Author-email: hello@elementl.com
License: Apache-2.0
Platform: UNKNOWN
Classifier: Programming Language :: Python :: 3.7
Classifier: Programming Language :: Python :: 3.8
Classifier: Programming Language :: Python :: 3.9
Classifier: License :: OSI Approved :: Apache Software License
Classifier: Operating System :: OS Independent
License-File: LICENSE
Requires-Dist: dagster (==1.0.5)
Requires-Dist: pandas
Requires-Dist: pandera (>=0.9.0)
Provides-Extra: test
Requires-Dist: pytest ; extra == 'test'
